meendag/__init__.py
meendag/apihelper.py
meendag/main.py
meendag/types.py
meendag/utils.py
meendag-0.0.0.dist-info/LICENSE
meendag-0.0.0.dist-info/METADATA
meendag-0.0.0.dist-info/WHEEL
meendag-0.0.0.dist-info/top_level.txt
meendag-0.0.0.dist-info/RECORD
