Metadata-Version: 2.1
Name: meendag
Version: 0.0.0
Summary: An unofficial SDK for Meendag.com help you to find name of the owner of the number
Home-page: https://github.com/TheAwiteb/meendag
Author: Awiteb
Author-email: Awiteb@hotmail.com
License: AGPL
Keywords: meendag,Meendag,number-owner
Platform: UNKNOWN
Classifier: Programming Language :: Python :: 3.8
Classifier: Programming Language :: Python :: 3.9
Classifier: Programming Language :: Python :: 3.10
Classifier: License :: OSI Approved :: GNU Affero General Public License v3
Classifier: Operating System :: OS Independent
Requires-Python: >=3.8
License-File: LICENSE
Requires-Dist: beautifulsoup4 (==4.10.0)
Requires-Dist: certifi (==2021.10.8)
Requires-Dist: charset-normalizer (==2.0.10)
Requires-Dist: idna (==3.3)
Requires-Dist: pydantic (==1.9.0)
Requires-Dist: requests (==2.27.1)
Requires-Dist: soupsieve (==2.3.1)
Requires-Dist: typing-extensions (==4.0.1)
Requires-Dist: urllib3 (==1.26.8)
